antom/__init__.py
antom/antom.py
weather_guodong-2.0.4.dist-info/METADATA
weather_guodong-2.0.4.dist-info/WHEEL
weather_guodong-2.0.4.dist-info/entry_points.txt
weather_guodong-2.0.4.dist-info/top_level.txt
weather_guodong-2.0.4.dist-info/RECORD
