Metadata-Version: 2.4
Name: weather-guodong
Version: 2.0.4
Summary: Antom支付接口集成工具（收银台模式）
Author-email: Your Name <your.email@example.com>
License-Expression: LicenseRef-Proprietary
Project-URL: Homepage, https://github.com/yourusername/weather-guodong
Project-URL: Documentation, https://github.com/yourusername/weather-guodong/wiki
Classifier: Programming Language :: Python :: 3.10
Classifier: Programming Language :: Python :: 3.11
Requires-Python: >=3.10
Requires-Dist: global-open-sdk-python>=1.4.4
Requires-Dist: mcp[cli]>=1.7.1
Requires-Dist: uuid>=1.30
